Metadata-Version: 2.4
Name: zenith-cli
Version: 0.1.2
Summary: Zenith Is A CLI-Based AI Coding Agent That Transforms Natural Language Into Efficient, Production-Ready Code!
Author-email: Rohit Vilas Ingole <rohit.vilas.ingole@gmail.com>
License: # The MIT License
Project-URL: Homepage, https://github.com/datarohit/zenith
Classifier: Programming Language :: Python :: 3
Classifier: License :: OSI Approved :: MIT License
Classifier: Operating System :: OS Independent
Requires-Python: >=3.13
Requires-Dist: rich-cli>=1.8.1
Requires-Dist: typer>=0.17.4
Requires-Dist: python-dotenv>=1.1.1
Requires-Dist: python-dateutil>=2.9.0
Requires-Dist: autogen-agentchat>=0.7.4
Requires-Dist: autogen-ext>=0.7.4
Requires-Dist: autogen-ext[openai]>=0.7.4
Provides-Extra: dev
Requires-Dist: pytest>=8.4.2; extra == "dev"
Requires-Dist: pytest-cov>=7.0.0; extra == "dev"
Requires-Dist: pytest-asyncio>=1.2.0; extra == "dev"
Requires-Dist: ruff>=0.13.0; extra == "dev"
